python_vncorenlp/__init__.py
python_vncorenlp/protocols.py
python_vncorenlp/vncorenlp.py
python_vncorenlp/data/vncorenlp.jar
python_vncorenlp-0.1.8.dist-info/LICENSE.txt
python_vncorenlp-0.1.8.dist-info/METADATA
python_vncorenlp-0.1.8.dist-info/WHEEL
python_vncorenlp-0.1.8.dist-info/top_level.txt
python_vncorenlp-0.1.8.dist-info/RECORD
