Metadata-Version: 2.1
Name: python-vncorenlp
Version: 0.1.8
Summary: python_vncorenlp
Home-page: https://github.com/NgHoangDat/python_vncorenlp.git
Author: nghoangdat
Author-email: 18.hoang.dat.12@gmail.com
License: UNKNOWN
Download-URL: https://github.com/NgHoangDat/python_vncorenlp/archive/v0.1.8.tar.gz
Keywords: python-vncorenlp vncorenlp nlp vietnamese-nlp parser word-segmentation tokenizer pos-tagger named-entity-recognition ner dependency-parser
Platform: UNKNOWN
Classifier: Programming Language :: Python :: 3
Classifier: License :: OSI Approved :: MIT License
Classifier: Operating System :: OS Independent
Classifier: Topic :: Text Processing :: Linguistic
Requires-Python: >=3.6
Requires-Dist: pyjnius
Requires-Dist: typing-extensions
